logger_utils/__init__.py
logger_utils/utils.py
secops_soar_mcp/__init__.py
secops_soar_mcp/bindings.py
secops_soar_mcp/case_management.py
secops_soar_mcp/http_client.py
secops_soar_mcp/server.py
secops_soar_mcp/marketplace/__init__.py
secops_soar_mcp/marketplace/activedirectory.py
secops_soar_mcp/marketplace/alexa.py
secops_soar_mcp/marketplace/algosec.py
secops_soar_mcp/marketplace/alienvaultti.py
secops_soar_mcp/marketplace/alienvaultusmanywhere.py
secops_soar_mcp/marketplace/alienvaultusmappliance.py
secops_soar_mcp/marketplace/amazonmacie.py
secops_soar_mcp/marketplace/anomali.py
secops_soar_mcp/marketplace/anomalistaxx.py
secops_soar_mcp/marketplace/anomalithreatstream.py
secops_soar_mcp/marketplace/any.run.py
secops_soar_mcp/marketplace/apivoid.py
secops_soar_mcp/marketplace/appsheet.py
secops_soar_mcp/marketplace/arcsight.py
secops_soar_mcp/marketplace/arcsightlogger.py
secops_soar_mcp/marketplace/area1.py
secops_soar_mcp/marketplace/armis.py
secops_soar_mcp/marketplace/atlassianconfluenceserver.py
secops_soar_mcp/marketplace/attivo.py
secops_soar_mcp/marketplace/automox.py
secops_soar_mcp/marketplace/awscloudtrail.py
secops_soar_mcp/marketplace/awscloudwatch.py
secops_soar_mcp/marketplace/awselasticcomputecloud(ec2).py
secops_soar_mcp/marketplace/awsguardduty.py
secops_soar_mcp/marketplace/awsiamaccessanalyzer.py
secops_soar_mcp/marketplace/awsidentityandaccessmanagement(iam).py
secops_soar_mcp/marketplace/awss3.py
secops_soar_mcp/marketplace/awssecurityhub.py
secops_soar_mcp/marketplace/awswaf.py
secops_soar_mcp/marketplace/axonius.py
secops_soar_mcp/marketplace/azureactivedirectory.py
secops_soar_mcp/marketplace/azureadidentityprotection.py
secops_soar_mcp/marketplace/azuresecuritycenter.py
secops_soar_mcp/marketplace/bitsight.py
secops_soar_mcp/marketplace/blueliv.py
secops_soar_mcp/marketplace/bmchelixremedyforce.py
secops_soar_mcp/marketplace/bmcremedyitsm.py
secops_soar_mcp/marketplace/bulkwhois.py
secops_soar_mcp/marketplace/carbonblackdefense.py
secops_soar_mcp-0.1.0.dist-info/METADATA
secops_soar_mcp-0.1.0.dist-info/WHEEL
secops_soar_mcp-0.1.0.dist-info/entry_points.txt
secops_soar_mcp-0.1.0.dist-info/top_level.txt
secops_soar_mcp-0.1.0.dist-info/RECORD
