Metadata-Version: 2.4
Name: secops-soar-mcp
Version: 0.1.0
Summary: Google SecOps SOAR MCP server
Author-email: Google SecOps Team <chronicle@google.com>
Project-URL: Homepage, https://github.com/google/mcp-security
Project-URL: Documentation, https://github.com/google/mcp-security/tree/main/server/secops-soar#readme
Project-URL: Repository, https://github.com/google/mcp-security/tree/main/server/secops-soar
Project-URL: Issues, https://github.com/google/mcp-security/issues
Keywords: google,security,chronicle,secops,soar,gti,mcp
Classifier: Programming Language :: Python :: 3
Classifier: Programming Language :: Python :: 3.11
Classifier: Topic :: Security
Requires-Python: >=3.11
Requires-Dist: aiohttp>=3.11.15
Requires-Dist: mcp[cli]>=1.4.1
Provides-Extra: test
Requires-Dist: pytest>=7.0.0; extra == "test"
Requires-Dist: pytest-asyncio>=0.21.0; extra == "test"
